streamlit_drawable_canvas/__init__.py
streamlit_drawable_canvas/frontend/build/asset-manifest.json
streamlit_drawable_canvas/frontend/build/index.html
streamlit_drawable_canvas/frontend/build/static/css/main.3a68977b.chunk.css
streamlit_drawable_canvas/frontend/build/static/css/main.3a68977b.chunk.css.map
streamlit_drawable_canvas/frontend/build/static/js/2.58380945.chunk.js
streamlit_drawable_canvas/frontend/build/static/js/2.58380945.chunk.js.LICENSE.txt
streamlit_drawable_canvas/frontend/build/static/js/2.58380945.chunk.js.map
streamlit_drawable_canvas/frontend/build/static/js/main.5369d588.chunk.js
streamlit_drawable_canvas/frontend/build/static/js/main.5369d588.chunk.js.map
streamlit_drawable_canvas/frontend/build/static/js/runtime-main.3def19be.js
streamlit_drawable_canvas/frontend/build/static/js/runtime-main.3def19be.js.map
streamlit_drawable_canvas_fix-0.9.8.dist-info/licenses/LICENSE
streamlit_drawable_canvas_fix-0.9.8.dist-info/METADATA
streamlit_drawable_canvas_fix-0.9.8.dist-info/WHEEL
streamlit_drawable_canvas_fix-0.9.8.dist-info/top_level.txt
streamlit_drawable_canvas_fix-0.9.8.dist-info/RECORD
