Metadata-Version: 2.4
Name: streamlit-drawable-canvas-fix
Version: 0.9.8
Summary: Fix of orignal streamlit-drawable-canvas for new streamlit versions.
Home-page: https://github.com/AndreasBauerGit/streamlit-drawable-canvas-fix
Author: Andreas Bauer
Author-email: Andreas.Bauer2@gmx.net
Requires-Python: >=3.6
License-File: LICENSE
Requires-Dist: Pillow
Requires-Dist: numpy
Requires-Dist: streamlit>=1.49.0
Dynamic: author
Dynamic: author-email
Dynamic: description
Dynamic: description-content-type
Dynamic: home-page
Dynamic: license-file
Dynamic: requires-dist
Dynamic: requires-python
Dynamic: summary
